flider/__init__.py
flider/__main__.py
flider/flider.py
flider/index.txt
flider/init.txt
flider/mysqlcontroller.txt
flider/scripts.txt
flider/server.txt
flider/style.txt
flider/user.txt
flider/users.txt
Flider-1.1.7.dist-info/LICENSE
Flider-1.1.7.dist-info/METADATA
Flider-1.1.7.dist-info/WHEEL
Flider-1.1.7.dist-info/top_level.txt
Flider-1.1.7.dist-info/RECORD
