Metadata-Version: 2.1
Name: Flider
Version: 1.1.7
Summary: A lightweight flask skeleton builder.
Home-page: https://github.com/trevorengen/flider
Author: Trevor Engen
Author-email: Trevorengen@gmail.com
License: UNKNOWN
Project-URL: Bug Tracker, https://github.com/trevorengen/flider/issues
Platform: UNKNOWN
Classifier: Programming Language :: Python :: 3
Classifier: License :: OSI Approved :: MIT License
Classifier: Operating System :: OS Independent
Requires-Python: >=3.6
License-File: LICENSE
